pesfit/__init__.py
pesfit/fitter.py
pesfit/istarmap.py
pesfit/lineshape.py
pesfit/metrics.py
pesfit/utils.py
pesfit-0.6.6.dist-info/LICENSE
pesfit-0.6.6.dist-info/METADATA
pesfit-0.6.6.dist-info/WHEEL
pesfit-0.6.6.dist-info/top_level.txt
pesfit-0.6.6.dist-info/RECORD
