Metadata-Version: 2.1
Name: pesfit
Version: 0.6.6
Summary: Multiband lineshape fitting routines for photoemission spectroscopy
Home-page: https://github.com/mpes-kit/pesfit
Author: R. Patrick Xian
Author-email: xrpatrick@gmail.com
License: MIT
Download-URL: https://github.com/mpes-kit/pesfit/tarball/0.6.6
Platform: UNKNOWN
Classifier: Development Status :: 3 - Alpha
Classifier: Intended Audience :: Developers
Classifier: Programming Language :: Python :: 3
Requires-Dist: lmfit
Requires-Dist: h5py
Requires-Dist: pandas
Requires-Dist: hdfio
Requires-Dist: dask
Requires-Dist: cloudpickle
Requires-Dist: sphinx
Requires-Dist: coverage
